setup.py
minio_sdk/__init__.py
minio_sdk/minio.py
minio_sdk.egg-info/PKG-INFO
minio_sdk.egg-info/SOURCES.txt
minio_sdk.egg-info/dependency_links.txt
minio_sdk.egg-info/requires.txt
minio_sdk.egg-info/top_level.txt