Metadata-Version: 2.1
Name: minio-sdk
Version: 1.0.1
Summary: python sdk for minio
Home-page: UNKNOWN
Author: Jucheng Mo
Author-email: mojucheng@bytedance.com
License: UNKNOWN
Platform: UNKNOWN
